gitview/__init__.py
gitview/branches.py
gitview/chunker.py
gitview/cli.py
gitview/extractor.py
gitview/index_writer.py
gitview/remote.py
gitview/storyteller.py
gitview/summarizer.py
gitview/writer.py
gitview/backends/__init__.py
gitview/backends/anthropic_backend.py
gitview/backends/base.py
gitview/backends/ollama_backend.py
gitview/backends/openai_backend.py
gitview/backends/router.py
gitview-0.1.3.dist-info/licenses/LICENSE
gitview-0.1.3.dist-info/METADATA
gitview-0.1.3.dist-info/WHEEL
gitview-0.1.3.dist-info/entry_points.txt
gitview-0.1.3.dist-info/top_level.txt
gitview-0.1.3.dist-info/RECORD
