Metadata-Version: 2.4
Name: gitview
Version: 0.1.3
Summary: Git history analyzer with LLM-powered narrative generation
Home-page: https://github.com/carstenbund/gitview
Author: GitView Contributors
Author-email: 
Maintainer: GitView Contributors
License: MIT
Project-URL: Homepage, https://github.com/carstenbund/gitview
Project-URL: Documentation, https://github.com/carstenbund/gitview/blob/main/README.md
Project-URL: Repository, https://github.com/carstenbund/gitview
Project-URL: Issues, https://github.com/carstenbund/gitview/issues
Keywords: git,history,analyzer,llm,narrative,ai,claude,openai,ollama
Classifier: Development Status :: 3 - Alpha
Classifier: Intended Audience :: Developers
Classifier: Intended Audience :: Information Technology
Classifier: Topic :: Software Development :: Version Control :: Git
Classifier: Topic :: Software Development :: Documentation
Classifier: Topic :: Text Processing :: Markup :: Markdown
Classifier: License :: OSI Approved :: MIT License
Classifier: Programming Language :: Python :: 3
Classifier: Programming Language :: Python :: 3.8
Classifier: Programming Language :: Python :: 3.9
Classifier: Programming Language :: Python :: 3.10
Classifier: Programming Language :: Python :: 3.11
Classifier: Programming Language :: Python :: 3.12
Classifier: Operating System :: OS Independent
Classifier: Environment :: Console
Requires-Python: >=3.8
License-File: LICENSE
Requires-Dist: anthropic>=0.39.0
Requires-Dist: openai>=1.0.0
Requires-Dist: requests>=2.31.0
Requires-Dist: gitpython>=3.1.40
Requires-Dist: python-dateutil>=2.8.2
Requires-Dist: click>=8.1.7
Requires-Dist: rich>=13.7.0
Requires-Dist: pydantic>=2.5.0
Dynamic: home-page
Dynamic: license-file
Dynamic: requires-python
